CHANGES.txt
LICENSE.txt
MANIFEST.in
README.rst
pyproject.toml
setup.cfg
setup.py
tox.ini
src/pyramid_csrf_multi_scheme/__init__.py
src/pyramid_csrf_multi_scheme.egg-info/PKG-INFO
src/pyramid_csrf_multi_scheme.egg-info/SOURCES.txt
src/pyramid_csrf_multi_scheme.egg-info/dependency_links.txt
src/pyramid_csrf_multi_scheme.egg-info/not-zip-safe
src/pyramid_csrf_multi_scheme.egg-info/requires.txt
src/pyramid_csrf_multi_scheme.egg-info/top_level.txt
src/pyramid_csrf_multi_scheme/debugtoolbar/__init__.py
src/pyramid_csrf_multi_scheme/debugtoolbar/panels/__init__.py
src/pyramid_csrf_multi_scheme/debugtoolbar/panels/csrf_multi_scheme.py
src/pyramid_csrf_multi_scheme/debugtoolbar/panels/templates/csrf_multi_scheme.dbtmako
tests/__init__.py
tests/test_csrf.py
tests/test_debugtoolbar.py