Metadata-Version: 2.1
Name: pyramid-csrf-multi-scheme
Version: 0.1.1
Summary: Provides for creating independent csrf tokens for the http and https schemes
Home-page: https://github.com/jvanasco/pyramid_csrf_multi_scheme
Author: Jonathan Vanasco
Author-email: jonathan@findmeon.com
License: BSD-derived (http://www.repoze.org/LICENSE.txt)
Keywords: web pyramid csrf
Platform: UNKNOWN
Classifier: Intended Audience :: Developers
Classifier: Framework :: Pyramid
Classifier: Programming Language :: Python
Classifier: Programming Language :: Python :: 2
Classifier: Programming Language :: Python :: 3
Classifier: License :: Repoze Public License
Provides-Extra: testing
